README.txt
ken.py
setup.py
ken.egg-info/PKG-INFO
ken.egg-info/SOURCES.txt
ken.egg-info/dependency_links.txt
ken.egg-info/top_level.txt