Metadata-Version: 1.0
Name: ken
Version: 9001.0.3
Summary: Ken is over 9000
Home-page: UNKNOWN
Author: Infoshift Inc
Author-email: me@jpanganiban.com
License: UNKNOWN
Platform: UNKNOWN
